.installed.cfg
CHANGES.txt
MANIFEST.in
README.rst
README.txt
bootstrap.py
buildout.cfg
setup.py
tus/__init__.py
tus.egg-info/PKG-INFO
tus.egg-info/SOURCES.txt
tus.egg-info/dependency_links.txt
tus.egg-info/entry_points.txt
tus.egg-info/not-zip-safe
tus.egg-info/requires.txt
tus.egg-info/top_level.txt
tus/tests/__init__.py
tus/tests/test_filter.py
tus/tests/test_plone.py
tus/tests/test_webob.py
tus/tests/files/test.txt