Metadata-Version: 1.1
Name: tus
Version: 1.0a1
Summary: tus
Home-page: UNKNOWN
Author: Nathan Van Gheem
Author-email: nathan@vangheem.us
License: UNKNOWN
Keywords: web pyramid pylons
Platform: UNKNOWN
Classifier: Programming Language :: Python
Classifier: Topic :: Internet :: WWW/HTTP
Classifier: Topic :: Internet :: WWW/HTTP :: WSGI :: Application
